ebpfcat/__init__.py
ebpfcat/arraymap.py
ebpfcat/bpf.py
ebpfcat/devices.py
ebpfcat/ebpf.py
ebpfcat/ebpf_test.py
ebpfcat/ebpfcat.py
ebpfcat/ethercat.py
ebpfcat/ethercat_test.py
ebpfcat/hashmap.py
ebpfcat/lock.py
ebpfcat/scripts.py
ebpfcat/serial.py
ebpfcat/terminals.py
ebpfcat/testdata.py
ebpfcat/util.py
ebpfcat/xdp.py
ebpfcat-0.7.0.dist-info/LICENSE
ebpfcat-0.7.0.dist-info/METADATA
ebpfcat-0.7.0.dist-info/WHEEL
ebpfcat-0.7.0.dist-info/entry_points.txt
ebpfcat-0.7.0.dist-info/top_level.txt
ebpfcat-0.7.0.dist-info/RECORD
