Metadata-Version: 2.2
Name: ebpfcat
Version: 0.7.0
Summary: An EtherCAT master written in Python using EBPF and XDP
Author: Martin Teichmann
Author-email: Martin Teichmann <martin.teichmann@gmail.com>
License-File: LICENSE
Dynamic: author
